CHANGELOG.txt
LICENCE.txt
MANIFEST.in
README.txt
setup.py
gmsdict2csv/__init__.py
gmsdict2csv.egg-info/PKG-INFO
gmsdict2csv.egg-info/SOURCES.txt
gmsdict2csv.egg-info/dependency_links.txt
gmsdict2csv.egg-info/top_level.txt